FileScanner/Scanner.py
FileScanner/__init__.py
filescanner-1.1.4.dist-info/METADATA
filescanner-1.1.4.dist-info/WHEEL
filescanner-1.1.4.dist-info/licenses/LICENSE
filescanner-1.1.4.dist-info/RECORD
