Metadata-Version: 2.1
Name: FileScanner
Version: 1.1.4
Summary: Scans files based on input array
Author-email: Ryan Sanders <rasanders22@gmail.com>
License-File: LICENSE
Classifier: License :: OSI Approved :: MIT License
Classifier: Operating System :: OS Independent
Classifier: Programming Language :: Python :: 3
Requires-Python: >=3.7
